<?xml version="1.0" encoding="UTF-8"?>

<container xmlns="http://www.symfony-project.org/schema/dic/services"
    xmlns:xsi="http://www.w3.org/2001/XMLSchema-instance"
    xsi:schemaLocation="http://www.symfony-project.org/schema/dic/services http://www.symfony-project.org/schema/dic/services/services-1.0.xsd">

    <parameters>
        <parameter key="payments.plugin_controller.class">Bundle\PaymentBundle\PluginController\EntityPluginController</parameter>
        <parameter key="payments.plugin_controller.options.financial_transaction_class">Bundle\PaymentBundle\Entity\FinancialTransaction</parameter>
        <parameter key="payments.plugin_controller.options.result_class">Bundle\PaymentBundle\PluginController\Result</parameter>
    </parameters>

    <services>
        <service id="payments.plugin_controller" class="%payments.plugin_controller.class%" alias="ppc">
            <argument type="collection">
                <argument key="financial_transaction_class">%payments.plugin_controller.options.financial_transaction_class%</argument>
                <argument key="result_class">%payments.plugin_controller.options.result_class%</argument>
            </argument>
        </service>
    </services>
</container>